prof_checker
tests
