Metadata-Version: 2.1
Name: prof-checker
Version: 1.0.2
Summary: Wrapper for profanity checker that can work on python services/scripts, similar to linters (e.g. pylint)
Home-page: https://github.com/ozychhi/prof-checker
Author: Tornike Gogniashvili
Author-email: t.gogniashvili@gmail.com
License: UNKNOWN
Platform: UNKNOWN
Classifier: Development Status :: 5 - Production/Stable
Classifier: Natural Language :: English
Classifier: Programming Language :: Python :: 3
Classifier: License :: OSI Approved :: MIT License
Classifier: Operating System :: OS Independent
Provides-Extra: dev
